<?xml version="1.0" encoding="utf-8" ?><dwsync><file name="kushi-ague.png" server="home622608119.1and1-data.host" local="3692107440" remote="3694495029" Dst="-1" /><file name="sushi-makipng.png" server="home622608119.1and1-data.host" local="3692064826" remote="3694495030" Dst="-1" /><file name="menu-chisai-charoleado-iconos-cocineros.png" server="home622608119.1and1-data.host" local="3692062548" remote="3694495030" Dst="-1" /><file name="menu-chisai-iconos-tipo-b.png" server="home622608119.1and1-data.host" local="3692063658" remote="3694495030" Dst="-1" /><file name="menu-chisai-iconos-tipo-a.png" server="home622608119.1and1-data.host" local="3692063646" remote="3694495031" Dst="-1" /><file name="yakimeshi.png" server="home622608119.1and1-data.host" local="3692107656" remote="3694495031" Dst="-1" /><file name="menu-chisai-charoleado-iconos-mesero.png" server="home622608119.1and1-data.host" local="3692062564" remote="3694495032" Dst="-1" /><file name="menu-chisai-charoleado-iconos-equipo-cocina-almomento.png" server="home622608119.1and1-data.host" local="3692062672" remote="3694495032" Dst="-1" /></dwsync>